backstrip/__init__.py
backstrip/_backplot.py
backstrip/_backstrip.py
backstrip/_get_bbox_generic.py
backstrip-0.2.4.dist-info/LICENSE
backstrip-0.2.4.dist-info/METADATA
backstrip-0.2.4.dist-info/WHEEL
backstrip-0.2.4.dist-info/top_level.txt
backstrip-0.2.4.dist-info/RECORD
